setup.cfg
setup.py
docker_etude/__init__.py
docker_etude/main.py
docker_etude.egg-info/PKG-INFO
docker_etude.egg-info/SOURCES.txt
docker_etude.egg-info/dependency_links.txt
docker_etude.egg-info/entry_points.txt
docker_etude.egg-info/not-zip-safe
docker_etude.egg-info/requires.txt
docker_etude.egg-info/top_level.txt
docker_etude/models/__init__.py
docker_etude/models/base.py
docker_etude/models/composition.py
docker_etude/models/network.py
docker_etude/models/options.py
docker_etude/models/service.py
docker_etude/models/validation.py
docker_etude/models/volume.py
docker_etude/sources/__init__.py
docker_etude/sources/base.py
docker_etude/sources/ecs.py
docker_etude/sources/localstack.py