Metadata-Version: 1.0
Name: docker-etude
Version: 0.5.0
Summary: Build Docker Compositions, Especially For Local Development
Home-page: https://github.com/globality-corp/docker-etude
Author: Globality Engineering
Author-email: engineering@globality.com
License: UNKNOWN
Keywords: docker
Platform: UNKNOWN
